mixed_effect.py
mixed_effect-0.0.1.dist-info/LICENSE
mixed_effect-0.0.1.dist-info/METADATA
mixed_effect-0.0.1.dist-info/WHEEL
mixed_effect-0.0.1.dist-info/top_level.txt
mixed_effect-0.0.1.dist-info/RECORD
