Metadata-Version: 2.1
Name: mixed-effect
Version: 0.0.1
Summary: Mixed effects analysis
Home-page: UNKNOWN
Author: Vinoth Loganathan
Author-email: <vinothloganathan@outlook.com>
License: UNKNOWN
Keywords: python,KPI,month,mom,yoy,wow,mix effects
Platform: UNKNOWN
Classifier: Development Status :: 1 - Planning
Classifier: Intended Audience :: Developers
Classifier: Intended Audience :: Information Technology
Classifier: Intended Audience :: Science/Research
Classifier: Programming Language :: Python :: 3
Classifier: Operating System :: Unix
Classifier: Operating System :: MacOS :: MacOS X
Classifier: Operating System :: Microsoft :: Windows
License-File: LICENSE
